cvjd_common/__init__.py
cvjd_common/py.typed
cvjd_common/log/__init__.py
cvjd_common/log/action_log.py
cvjd_common/log/action_log_callback.py
cvjd_common/log/action_log_model.py
cvjd_common/log/auth_caller_retrieval.py
cvjd_common/log/caller_retrieval.py
cvjd_common/log/http_header_caller_retrieval.py
cvjd_common/models/__init__.py
cvjd_common/models/cv.py
cvjd_common/models/cv_jd_gap.py
cvjd_common/models/cv_match.py
cvjd_common/models/jd.py
cvjd_common/models/job.py
cvjd_common/persistent/__init__.py
cvjd_common/persistent/file_backend.py
cvjd_common/persistent/persistent_base.py
cvjd_common/persistent/redis_backend.py
kylg_cvjdcommon-0.1.8.dist-info/LICENSE
kylg_cvjdcommon-0.1.8.dist-info/METADATA
kylg_cvjdcommon-0.1.8.dist-info/NOTICE
kylg_cvjdcommon-0.1.8.dist-info/WHEEL
kylg_cvjdcommon-0.1.8.dist-info/top_level.txt
kylg_cvjdcommon-0.1.8.dist-info/RECORD
