Metadata-Version: 2.1
Name: kylg-cvjdcommon
Version: 0.1.8
Summary: Common code library for kylg cvjd
Home-page: https://github.com/kylg/cvjd
Maintainer: kylg
Maintainer-email: info@kylg.org
License: UNKNOWN
Platform: UNKNOWN
Requires-Python: >=3.6
Requires-Dist: flask (>=1.0.2)
